relistats/__init__.py
relistats/__main__.py
relistats/binom_fin.py
relistats/binomial.py
relistats/intervals.py
relistats/percentile.py
relistats-1.2.0.dist-info/METADATA
relistats-1.2.0.dist-info/WHEEL
relistats-1.2.0.dist-info/licenses/LICENSE
relistats-1.2.0.dist-info/RECORD
