Metadata-Version: 2.1
Name: relistats
Version: 1.2.0
Summary: Reliable Statistics
Project-URL: Homepage, https://github.com/sanjaymjoshi/relistats
Project-URL: Documentation, https://relistats.readthedocs.io/en/latest/
Project-URL: Repository, https://github.com/sanjaymjoshi/relistats
Project-URL: Bug Tracker, https://github.com/sanjaymjoshi/relistats/issues
Project-URL: Changelog, https://github.com/sanjaymjoshi/relistats/blob/main/CHANGELOG.md
Author-email: Sanjay Joshi <sanjaymjoshi@iitbombay.org>
Maintainer-email: Sanjay Joshi <sanjaymjoshi@iitbombay.org>
License: MIT License
License-File: LICENSE
Keywords: assurance,confidence,percentile,reliability,statistics
Classifier: Development Status :: 4 - Beta
Classifier: Programming Language :: Python
Requires-Python: >=3.10
Requires-Dist: scipy
